LICENSE
README.md
setup.py
cuneb_chenn.egg-info/PKG-INFO
cuneb_chenn.egg-info/SOURCES.txt
cuneb_chenn.egg-info/dependency_links.txt
cuneb_chenn.egg-info/requires.txt
cuneb_chenn.egg-info/top_level.txt
src/cuneb/.env
src/cuneb/CMakeLists.txt
src/cuneb/__init__.py
src/cuneb/cuneb.cpp
src/cuneb/cuneb.cu
test/test_cuneb.py